.gitignore
ArtisticLicense20.html
LICENSE.txt
MANIFEST.in
README.md
licenses-amendments.txt
setup.cfg
setup.py
namedtupledefs/__init__.py
namedtupledefs/namedtuple_original.py
namedtupledefs2.egg-info/PKG-INFO
namedtupledefs2.egg-info/SOURCES.txt
namedtupledefs2.egg-info/dependency_links.txt
namedtupledefs2.egg-info/not-zip-safe
namedtupledefs2.egg-info/top_level.txt
testdata/__init__.py
testdata/namedtuplex_testdata/__init__.py
tests/.gitignore
tests/__init__$py.class
tests/__init__.py
tests/__init__.pyc
tests/__pycache__/__init__.cpython-36.pyc
tests/__pycache__/__init__.cpython-38.pyc
tests/__pycache__/__init__.pypy3-510.pyc
tests/namedtupledefs_tests/CallCase$py.class
tests/namedtupledefs_tests/CallCase.py
tests/namedtupledefs_tests/CallCase.pyc
tests/namedtupledefs_tests/__init__$py.class
tests/namedtupledefs_tests/__init__.py
tests/namedtupledefs_tests/__init__.pyc
tests/namedtupledefs_tests/30_libs/__init__$py.class
tests/namedtupledefs_tests/30_libs/__init__.py
tests/namedtupledefs_tests/30_libs/__init__.pyc
tests/namedtupledefs_tests/30_libs/__pycache__/__init__.cpython-36.pyc
tests/namedtupledefs_tests/30_libs/__pycache__/__init__.cpython-38.pyc
tests/namedtupledefs_tests/30_libs/__pycache__/__init__.pypy3-510.pyc
tests/namedtupledefs_tests/30_libs/namedtupledefs/__init__$py.class
tests/namedtupledefs_tests/30_libs/namedtupledefs/__init__.py
tests/namedtupledefs_tests/30_libs/namedtupledefs/__init__.pyc
tests/namedtupledefs_tests/30_libs/namedtupledefs/__pycache__/__init__.cpython-36.pyc
tests/namedtupledefs_tests/30_libs/namedtupledefs/__pycache__/__init__.cpython-38.pyc
tests/namedtupledefs_tests/30_libs/namedtupledefs/__pycache__/__init__.pypy3-510.pyc
tests/namedtupledefs_tests/30_libs/namedtupledefs/class_typename/__init__$py.class
tests/namedtupledefs_tests/30_libs/namedtupledefs/class_typename/__init__.py
tests/namedtupledefs_tests/30_libs/namedtupledefs/class_typename/__init__.pyc
tests/namedtupledefs_tests/30_libs/namedtupledefs/class_typename/__pycache__/__init__.cpython-36.pyc
tests/namedtupledefs_tests/30_libs/namedtupledefs/class_typename/__pycache__/__init__.cpython-38.pyc
