Metadata-Version: 1.2
Name: namedtupledefs2
Version: 0.1.21
Summary: Extended 'namedtuple' by default values.
Home-page: https://sourceforge.net/projects/namedtupledefs/
Author: Arno-Can Uestuensoez
Author-email: acue_sf2@sourceforge.net
Maintainer: acue
Maintainer-email: acue_sf2@sourceforge.net
License: Artistic-License-2.0 + Forced-Fairplay-Constraints
Download-URL: https://sourceforge.net/projects/namedtupledefs/files/
Project-URL: documents, https://namedtupledefs.sourceforge.io/
Project-URL: downloads, https://pypi.org/project/namedtupledefs/
Project-URL: source2, https://bitbucket.org/acue/namedtupledefs/
Project-URL: source, https://github.com/ArnoCan/namedtupledefs/
Project-URL: downloads1, https://sourceforge.net/projects/namedtupledefs/
Project-URL: source1, https://sourceforge.net/projects/namedtupledefs/
Project-URL: tracker, https://github.com/ArnoCan/namedtupledefs/issues
Project-URL: home, https://sourceforge.net/projects/namedtupledefs"
Project-URL: runtimerepo, https://pypi.org/project/namedtupledefs/
Keywords: ARM,GhostBSD,LinuxMint,Manjaro,TrueOS,collections.namedtuple collections,defaults fields,fielddefaults,fieldnames,fields,namedtuple,namedtuples,Aix,Alpine,AlpineLinux,Arch,ArchLinux,ArchLinuxARM,Armbian,BSD,BlackArch,BlackArchLinux,CPython,CentOS,Cygwin,Darwin,Debian,Distribution,DragonFlyBSD,Fedora,FigureWrap,FreeBSD,Gentoo,HP-UX,IPython,ImageWrap,IronPython,Java,Java,Jython,Kali,KaliLinux,Linux,MacOS,Minix,Minx3,NetBSD,OS-X,OpenBSD,OpenSUSE,OpenWRT,PyPy,Python2,Python3,RHEL,Raspbian,
Platform: Aix
Platform: GhostBSD
Platform: LinuxMint
Platform: Manjaro
Platform: TrueOS
Platform: AlpineLinux
Platform: ArchLinux
Platform: ArchLinuxARM
Platform: Armbian
Platform: BlackArchLinux
Platform: CentOS
Platform: Cygwin
Platform: Darwin
Platform: Debian
Platform: DragonFlyBSD
Platform: FedoraLinux
Platform: FreeBSD
Platform: GentooLinux
Platform: HP-UX
Platform: KaliLinux
Platform: MacOS
Platform: Minix
Platform: Minx3
Platform: NetBSD
Platform: OS-X
Platform: OpenBSD
Platform: OpenSUSE
Platform: OpenWRT
Platform: RHEL
Platform: Raspbian
Platform: ReactOS
Platform: SLES
Platform: Solaris
Platform: SuSE
Platform: SunOS
Platform: SunOS5
Platform: Ubuntu
Platform: Unix
Platform: Windows10
Platform: Windows2003
Platform: Windows2008
Platform: Windows2010
Platform: Windows2012
Platform: Windows2016
Platform: Windows2019
Platform: Windows2019se
Platform: Windows7
Platform: Windows8
Platform: WindowsXP
Classifier: Framework :: Setuptools Plugin
Classifier: Development Status :: 4 - Beta
Classifier: Environment :: Console
Classifier: Environment :: MacOS X
Classifier: Environment :: Other Environment
Classifier: Environment :: Win32 (MS Windows)
Classifier: Environment :: X11 Applications
Classifier: Framework :: IPython
Classifier: Intended Audience :: Developers
Classifier: Intended Audience :: System Administrators
Classifier: License :: Free To Use But Restricted
Classifier: License :: OSI Approved :: Artistic License
Classifier: Natural Language :: English
Classifier: Operating System :: MacOS :: MacOS X
Classifier: Operating System :: Microsoft :: Windows
Classifier: Operating System :: Other OS
Classifier: Operating System :: POSIX
Classifier: Operating System :: POSIX :: BSD :: FreeBSD
Classifier: Operating System :: POSIX :: BSD :: OpenBSD
Classifier: Operating System :: POSIX :: Linux
Classifier: Operating System :: POSIX :: Other
Classifier: Operating System :: POSIX :: SunOS/Solaris
Classifier: Operating System :: Unix
Classifier: Programming Language :: Python :: 2
Classifier: Programming Language :: Python :: 2.7
Classifier: Programming Language :: Python :: Implementation :: CPython
Classifier: Programming Language :: Python :: Implementation :: IronPython
Classifier: Programming Language :: Python :: Implementation :: Jython
Classifier: Programming Language :: Python :: Implementation :: PyPy
Classifier: Topic :: Software Development
Classifier: Topic :: Software Development :: Libraries
Classifier: Topic :: Software Development :: Libraries :: Python Modules
